main.py
inventree_server-0.17.4.dist-info/METADATA
inventree_server-0.17.4.dist-info/WHEEL
inventree_server-0.17.4.dist-info/top_level.txt
inventree_server-0.17.4.dist-info/RECORD
