Metadata-Version: 2.4
Name: inventree-server
Version: 0.17.4
Summary: Constraint dummy
